aiopg_listen/__init__.py
aiopg_listen/listener.py
aiopg_listen/py.typed
aiopg_listen-0.0.7.dist-info/LICENSE
aiopg_listen-0.0.7.dist-info/METADATA
aiopg_listen-0.0.7.dist-info/WHEEL
aiopg_listen-0.0.7.dist-info/top_level.txt
aiopg_listen-0.0.7.dist-info/RECORD
