Metadata-Version: 2.1
Name: aiopg-listen
Version: 0.0.7
Summary: Helps to use PostgreSQL listen/notify with aiopg
Home-page: https://github.com/Pliner/aiopg-listen
Author: Yury Pliner
Author-email: yury.pliner@gmail.com
License: MIT
Platform: macOS
Platform: POSIX
Platform: Windows
Classifier: License :: OSI Approved :: MIT License
Classifier: Intended Audience :: Developers
Classifier: Programming Language :: Python :: 3
Classifier: Programming Language :: Python :: 3 :: Only
Classifier: Programming Language :: Python :: 3.8
Classifier: Programming Language :: Python :: 3.9
Classifier: Programming Language :: Python :: 3.10
Classifier: Programming Language :: Python :: 3.11
Classifier: Operating System :: OS Independent
Classifier: Environment :: Web Environment
Classifier: Development Status :: 5 - Production/Stable
Classifier: Framework :: AsyncIO
Classifier: Typing :: Typed
Requires-Python: >=3.8
License-File: LICENSE
Requires-Dist: aiopg (>=1.4.0)
Requires-Dist: async-timeout (<5.0,>=3.0) ; python_version < "3.11"
